kwutil/__init__.py
kwutil/copy_manager.py
kwutil/copy_manager.pyi
kwutil/fsops_managers.py
kwutil/partial_format.py
kwutil/partial_format.pyi
kwutil/process_context.py
kwutil/py.typed
kwutil/slugify_ext.py
kwutil/slugify_ext.pyi
kwutil/util_dotdict.py
kwutil/util_environ.py
kwutil/util_environ.pyi
kwutil/util_eval.py
kwutil/util_eval.pyi
kwutil/util_exception.py
kwutil/util_hardware.py
kwutil/util_iter.py
kwutil/util_json.py
kwutil/util_json.pyi
kwutil/util_locks.py
kwutil/util_locks.pyi
kwutil/util_logging.py
kwutil/util_math.py
kwutil/util_parallel.py
kwutil/util_parallel.pyi
kwutil/util_path.py
kwutil/util_path.pyi
kwutil/util_pattern.py
kwutil/util_pattern.pyi
kwutil/util_progress.py
kwutil/util_progress.pyi
kwutil/util_prompt.py
kwutil/util_random.py
kwutil/util_resources.py
kwutil/util_resources.pyi
kwutil/util_rich.py
kwutil/util_time.py
kwutil/util_time.pyi
kwutil/util_units.py
kwutil/util_windows.py
kwutil/util_windows.pyi
kwutil/util_xml.py
kwutil/util_yaml.py
kwutil/util_yaml.pyi
kwutil-0.3.8.dist-info/licenses/LICENSE
kwutil-0.3.8.dist-info/METADATA
kwutil-0.3.8.dist-info/WHEEL
kwutil-0.3.8.dist-info/top_level.txt
kwutil-0.3.8.dist-info/RECORD
