Metadata-Version: 2.4
Name: kwutil
Version: 0.3.8
Summary: The kwutil module
Home-page: https://gitlab.kitware.com/computer-vision/kwutil
Author: Jon Crall
Author-email: jon.crall@kitware.com
License: Apache 2
Classifier: Development Status :: 3 - Alpha
Classifier: Intended Audience :: Developers
Classifier: Topic :: Software Development :: Libraries :: Python Modules
Classifier: Topic :: Utilities
Classifier: License :: OSI Approved :: Apache Software License
Classifier: Programming Language :: Python :: 3.8
Classifier: Programming Language :: Python :: 3.9
Classifier: Programming Language :: Python :: 3.10
Classifier: Programming Language :: Python :: 3.11
Classifier: Programming Language :: Python :: 3.12
Classifier: Programming Language :: Python :: 3.13
Requires-Python: >=3.8
License-File: LICENSE
Requires-Dist: ubelt>=1.3.6
Requires-Dist: lazy_loader>=0.1; python_version >= "3.7"
Requires-Dist: progiter>=1.1.0
Provides-Extra: all
Requires-Dist: ubelt>=1.3.6; extra == "all"
Requires-Dist: lazy_loader>=0.1; python_version >= "3.7" and extra == "all"
Requires-Dist: progiter>=1.1.0; extra == "all"
Requires-Dist: xdoctest>=1.1.5; extra == "all"
Requires-Dist: pytest>=6.2.5; python_version >= "3.10.0" and extra == "all"
Requires-Dist: pytest>=6.2.4; (python_version < "3.10.0" and python_version >= "3.7.0") and extra == "all"
Requires-Dist: pytest-cov>=3.0.0; python_version >= "3.6.0" and extra == "all"
Requires-Dist: pytest-timeout>=1.4.2; extra == "all"
Requires-Dist: coverage>=6.1.1; python_version >= "3.10" and extra == "all"
Requires-Dist: coverage>=5.3.1; (python_version < "3.10" and python_version >= "3.9") and extra == "all"
Requires-Dist: coverage>=6.1.1; (python_version < "3.9" and python_version >= "3.8") and extra == "all"
Requires-Dist: numpy>=2.1.0; (python_version < "4.0" and python_version >= "3.13") and extra == "all"
Requires-Dist: numpy>=1.26.0; (python_version < "3.13" and python_version >= "3.12") and extra == "all"
Requires-Dist: numpy>=1.23.2; (python_version < "3.12" and python_version >= "3.11") and extra == "all"
Requires-Dist: numpy>=1.21.6; (python_version < "3.11" and python_version >= "3.10") and extra == "all"
Requires-Dist: numpy>=1.19.3; (python_version < "3.10" and python_version >= "3.6") and extra == "all"
Requires-Dist: py-cpuinfo>=9.0.0; (python_version < "4.0" and python_version >= "3.13") and extra == "all"
Requires-Dist: py-cpuinfo>=9.0.0; (python_version < "3.13" and python_version >= "3.6") and extra == "all"
Requires-Dist: fasteners>=0.16.3; extra == "all"
Requires-Dist: text_unidecode>=1.3; extra == "all"
Requires-Dist: pytimeparse>=1.1.8; extra == "all"
Requires-Dist: parse>=1.19.0; extra == "all"
Requires-Dist: pint>=0.24.4; (python_version < "4.0" and python_version >= "3.13") and extra == "all"
Requires-Dist: pint>=0.23; (python_version < "3.13" and python_version >= "3.12") and extra == "all"
Requires-Dist: pint>=0.18; (python_version < "3.12" and python_version >= "3.11") and extra == "all"
Requires-Dist: pint>=0.18; (python_version < "3.11" and python_version >= "3.10") and extra == "all"
Requires-Dist: pint>=0.18; (python_version < "3.10" and python_version >= "3.9") and extra == "all"
Requires-Dist: pint>=0.18; (python_version < "3.9" and python_version >= "3.8") and extra == "all"
Requires-Dist: python_dateutil>=2.8.2; extra == "all"
Requires-Dist: rich>=12.3.0; extra == "all"
Requires-Dist: psutil>=5.9.6; (python_version < "4.0" and python_version >= "3.12") and extra == "all"
Requires-Dist: psutil>=5.9.1; (python_version < "3.12" and python_version >= "3.11") and extra == "all"
Requires-Dist: psutil>=5.9.1; (python_version < "3.11" and python_version >= "3.10") and extra == "all"
Requires-Dist: psutil>=5.7.3; (python_version < "3.10" and python_version >= "3.9") and extra == "all"
Requires-Dist: psutil>=5.6.3; (python_version < "3.9" and python_version >= "3.8") and extra == "all"
Requires-Dist: ruamel.yaml>=0.17.22; extra == "all"
Requires-Dist: PyYAML>=6.0.1; (python_version < "4.0" and python_version >= "3.12") and extra == "all"
Requires-Dist: PyYAML>=6.0; python_version < "3.12" and extra == "all"
Requires-Dist: pygtrie>=2.5.0; extra == "all"
Provides-Extra: runtime
Requires-Dist: ubelt>=1.3.6; extra == "runtime"
Requires-Dist: lazy_loader>=0.1; python_version >= "3.7" and extra == "runtime"
Requires-Dist: progiter>=1.1.0; extra == "runtime"
Provides-Extra: tests
Requires-Dist: xdoctest>=1.1.5; extra == "tests"
Requires-Dist: pytest>=6.2.5; python_version >= "3.10.0" and extra == "tests"
Requires-Dist: pytest>=6.2.4; (python_version < "3.10.0" and python_version >= "3.7.0") and extra == "tests"
Requires-Dist: pytest-cov>=3.0.0; python_version >= "3.6.0" and extra == "tests"
Requires-Dist: pytest-timeout>=1.4.2; extra == "tests"
Requires-Dist: coverage>=6.1.1; python_version >= "3.10" and extra == "tests"
Requires-Dist: coverage>=5.3.1; (python_version < "3.10" and python_version >= "3.9") and extra == "tests"
Requires-Dist: coverage>=6.1.1; (python_version < "3.9" and python_version >= "3.8") and extra == "tests"
Provides-Extra: optional
Requires-Dist: numpy>=2.1.0; (python_version < "4.0" and python_version >= "3.13") and extra == "optional"
Requires-Dist: numpy>=1.26.0; (python_version < "3.13" and python_version >= "3.12") and extra == "optional"
Requires-Dist: numpy>=1.23.2; (python_version < "3.12" and python_version >= "3.11") and extra == "optional"
Requires-Dist: numpy>=1.21.6; (python_version < "3.11" and python_version >= "3.10") and extra == "optional"
Requires-Dist: numpy>=1.19.3; (python_version < "3.10" and python_version >= "3.6") and extra == "optional"
Requires-Dist: py-cpuinfo>=9.0.0; (python_version < "4.0" and python_version >= "3.13") and extra == "optional"
Requires-Dist: py-cpuinfo>=9.0.0; (python_version < "3.13" and python_version >= "3.6") and extra == "optional"
Requires-Dist: fasteners>=0.16.3; extra == "optional"
Requires-Dist: text_unidecode>=1.3; extra == "optional"
Requires-Dist: pytimeparse>=1.1.8; extra == "optional"
Requires-Dist: parse>=1.19.0; extra == "optional"
Requires-Dist: pint>=0.24.4; (python_version < "4.0" and python_version >= "3.13") and extra == "optional"
Requires-Dist: pint>=0.23; (python_version < "3.13" and python_version >= "3.12") and extra == "optional"
Requires-Dist: pint>=0.18; (python_version < "3.12" and python_version >= "3.11") and extra == "optional"
Requires-Dist: pint>=0.18; (python_version < "3.11" and python_version >= "3.10") and extra == "optional"
Requires-Dist: pint>=0.18; (python_version < "3.10" and python_version >= "3.9") and extra == "optional"
Requires-Dist: pint>=0.18; (python_version < "3.9" and python_version >= "3.8") and extra == "optional"
Requires-Dist: python_dateutil>=2.8.2; extra == "optional"
Requires-Dist: rich>=12.3.0; extra == "optional"
Requires-Dist: psutil>=5.9.6; (python_version < "4.0" and python_version >= "3.12") and extra == "optional"
Requires-Dist: psutil>=5.9.1; (python_version < "3.12" and python_version >= "3.11") and extra == "optional"
Requires-Dist: psutil>=5.9.1; (python_version < "3.11" and python_version >= "3.10") and extra == "optional"
Requires-Dist: psutil>=5.7.3; (python_version < "3.10" and python_version >= "3.9") and extra == "optional"
Requires-Dist: psutil>=5.6.3; (python_version < "3.9" and python_version >= "3.8") and extra == "optional"
Requires-Dist: ruamel.yaml>=0.17.22; extra == "optional"
Requires-Dist: PyYAML>=6.0.1; (python_version < "4.0" and python_version >= "3.12") and extra == "optional"
Requires-Dist: PyYAML>=6.0; python_version < "3.12" and extra == "optional"
Requires-Dist: pygtrie>=2.5.0; extra == "optional"
Provides-Extra: docs
Requires-Dist: sphinx>=5.0.1; extra == "docs"
Requires-Dist: sphinx-autobuild>=2021.3.14; extra == "docs"
Requires-Dist: sphinx_rtd_theme>=1.0.0; extra == "docs"
Requires-Dist: sphinxcontrib-napoleon>=0.7; extra == "docs"
Requires-Dist: sphinx-autoapi>=1.8.4; extra == "docs"
Requires-Dist: Pygments>=2.9.0; extra == "docs"
Requires-Dist: myst_parser>=0.18.0; extra == "docs"
Requires-Dist: sphinx-reredirects>=0.0.1; extra == "docs"
Provides-Extra: linting
Requires-Dist: flake8>=5.0.0; extra == "linting"
Provides-Extra: all-strict
Requires-Dist: ubelt==1.3.6; extra == "all-strict"
Requires-Dist: lazy_loader==0.1; python_version >= "3.7" and extra == "all-strict"
Requires-Dist: progiter==1.1.0; extra == "all-strict"
Requires-Dist: xdoctest==1.1.5; extra == "all-strict"
Requires-Dist: pytest==6.2.5; python_version >= "3.10.0" and extra == "all-strict"
Requires-Dist: pytest==6.2.4; (python_version < "3.10.0" and python_version >= "3.7.0") and extra == "all-strict"
Requires-Dist: pytest-cov==3.0.0; python_version >= "3.6.0" and extra == "all-strict"
Requires-Dist: pytest-timeout==1.4.2; extra == "all-strict"
Requires-Dist: coverage==6.1.1; python_version >= "3.10" and extra == "all-strict"
Requires-Dist: coverage==5.3.1; (python_version < "3.10" and python_version >= "3.9") and extra == "all-strict"
Requires-Dist: coverage==6.1.1; (python_version < "3.9" and python_version >= "3.8") and extra == "all-strict"
Requires-Dist: numpy==2.1.0; (python_version < "4.0" and python_version >= "3.13") and extra == "all-strict"
Requires-Dist: numpy==1.26.0; (python_version < "3.13" and python_version >= "3.12") and extra == "all-strict"
Requires-Dist: numpy==1.23.2; (python_version < "3.12" and python_version >= "3.11") and extra == "all-strict"
Requires-Dist: numpy==1.21.6; (python_version < "3.11" and python_version >= "3.10") and extra == "all-strict"
Requires-Dist: numpy==1.19.3; (python_version < "3.10" and python_version >= "3.6") and extra == "all-strict"
Requires-Dist: py-cpuinfo==9.0.0; (python_version < "4.0" and python_version >= "3.13") and extra == "all-strict"
Requires-Dist: py-cpuinfo==9.0.0; (python_version < "3.13" and python_version >= "3.6") and extra == "all-strict"
Requires-Dist: fasteners==0.16.3; extra == "all-strict"
Requires-Dist: text_unidecode==1.3; extra == "all-strict"
Requires-Dist: pytimeparse==1.1.8; extra == "all-strict"
Requires-Dist: parse==1.19.0; extra == "all-strict"
Requires-Dist: pint==0.24.4; (python_version < "4.0" and python_version >= "3.13") and extra == "all-strict"
Requires-Dist: pint==0.23; (python_version < "3.13" and python_version >= "3.12") and extra == "all-strict"
Requires-Dist: pint==0.18; (python_version < "3.12" and python_version >= "3.11") and extra == "all-strict"
Requires-Dist: pint==0.18; (python_version < "3.11" and python_version >= "3.10") and extra == "all-strict"
Requires-Dist: pint==0.18; (python_version < "3.10" and python_version >= "3.9") and extra == "all-strict"
Requires-Dist: pint==0.18; (python_version < "3.9" and python_version >= "3.8") and extra == "all-strict"
Requires-Dist: python_dateutil==2.8.2; extra == "all-strict"
Requires-Dist: rich==12.3.0; extra == "all-strict"
Requires-Dist: psutil==5.9.6; (python_version < "4.0" and python_version >= "3.12") and extra == "all-strict"
Requires-Dist: psutil==5.9.1; (python_version < "3.12" and python_version >= "3.11") and extra == "all-strict"
Requires-Dist: psutil==5.9.1; (python_version < "3.11" and python_version >= "3.10") and extra == "all-strict"
Requires-Dist: psutil==5.7.3; (python_version < "3.10" and python_version >= "3.9") and extra == "all-strict"
Requires-Dist: psutil==5.6.3; (python_version < "3.9" and python_version >= "3.8") and extra == "all-strict"
Requires-Dist: ruamel.yaml==0.17.22; extra == "all-strict"
Requires-Dist: PyYAML==6.0.1; (python_version < "4.0" and python_version >= "3.12") and extra == "all-strict"
Requires-Dist: PyYAML==6.0; python_version < "3.12" and extra == "all-strict"
Requires-Dist: pygtrie==2.5.0; extra == "all-strict"
Provides-Extra: runtime-strict
Requires-Dist: ubelt==1.3.6; extra == "runtime-strict"
Requires-Dist: lazy_loader==0.1; python_version >= "3.7" and extra == "runtime-strict"
Requires-Dist: progiter==1.1.0; extra == "runtime-strict"
Provides-Extra: tests-strict
Requires-Dist: xdoctest==1.1.5; extra == "tests-strict"
Requires-Dist: pytest==6.2.5; python_version >= "3.10.0" and extra == "tests-strict"
Requires-Dist: pytest==6.2.4; (python_version < "3.10.0" and python_version >= "3.7.0") and extra == "tests-strict"
Requires-Dist: pytest-cov==3.0.0; python_version >= "3.6.0" and extra == "tests-strict"
Requires-Dist: pytest-timeout==1.4.2; extra == "tests-strict"
Requires-Dist: coverage==6.1.1; python_version >= "3.10" and extra == "tests-strict"
Requires-Dist: coverage==5.3.1; (python_version < "3.10" and python_version >= "3.9") and extra == "tests-strict"
Requires-Dist: coverage==6.1.1; (python_version < "3.9" and python_version >= "3.8") and extra == "tests-strict"
Provides-Extra: optional-strict
Requires-Dist: numpy==2.1.0; (python_version < "4.0" and python_version >= "3.13") and extra == "optional-strict"
Requires-Dist: numpy==1.26.0; (python_version < "3.13" and python_version >= "3.12") and extra == "optional-strict"
Requires-Dist: numpy==1.23.2; (python_version < "3.12" and python_version >= "3.11") and extra == "optional-strict"
Requires-Dist: numpy==1.21.6; (python_version < "3.11" and python_version >= "3.10") and extra == "optional-strict"
Requires-Dist: numpy==1.19.3; (python_version < "3.10" and python_version >= "3.6") and extra == "optional-strict"
Requires-Dist: py-cpuinfo==9.0.0; (python_version < "4.0" and python_version >= "3.13") and extra == "optional-strict"
Requires-Dist: py-cpuinfo==9.0.0; (python_version < "3.13" and python_version >= "3.6") and extra == "optional-strict"
Requires-Dist: fasteners==0.16.3; extra == "optional-strict"
Requires-Dist: text_unidecode==1.3; extra == "optional-strict"
Requires-Dist: pytimeparse==1.1.8; extra == "optional-strict"
Requires-Dist: parse==1.19.0; extra == "optional-strict"
Requires-Dist: pint==0.24.4; (python_version < "4.0" and python_version >= "3.13") and extra == "optional-strict"
Requires-Dist: pint==0.23; (python_version < "3.13" and python_version >= "3.12") and extra == "optional-strict"
Requires-Dist: pint==0.18; (python_version < "3.12" and python_version >= "3.11") and extra == "optional-strict"
Requires-Dist: pint==0.18; (python_version < "3.11" and python_version >= "3.10") and extra == "optional-strict"
Requires-Dist: pint==0.18; (python_version < "3.10" and python_version >= "3.9") and extra == "optional-strict"
Requires-Dist: pint==0.18; (python_version < "3.9" and python_version >= "3.8") and extra == "optional-strict"
Requires-Dist: python_dateutil==2.8.2; extra == "optional-strict"
Requires-Dist: rich==12.3.0; extra == "optional-strict"
Requires-Dist: psutil==5.9.6; (python_version < "4.0" and python_version >= "3.12") and extra == "optional-strict"
Requires-Dist: psutil==5.9.1; (python_version < "3.12" and python_version >= "3.11") and extra == "optional-strict"
Requires-Dist: psutil==5.9.1; (python_version < "3.11" and python_version >= "3.10") and extra == "optional-strict"
Requires-Dist: psutil==5.7.3; (python_version < "3.10" and python_version >= "3.9") and extra == "optional-strict"
Requires-Dist: psutil==5.6.3; (python_version < "3.9" and python_version >= "3.8") and extra == "optional-strict"
Requires-Dist: ruamel.yaml==0.17.22; extra == "optional-strict"
Requires-Dist: PyYAML==6.0.1; (python_version < "4.0" and python_version >= "3.12") and extra == "optional-strict"
Requires-Dist: PyYAML==6.0; python_version < "3.12" and extra == "optional-strict"
Requires-Dist: pygtrie==2.5.0; extra == "optional-strict"
Provides-Extra: docs-strict
Requires-Dist: sphinx==5.0.1; extra == "docs-strict"
Requires-Dist: sphinx-autobuild==2021.3.14; extra == "docs-strict"
Requires-Dist: sphinx_rtd_theme==1.0.0; extra == "docs-strict"
Requires-Dist: sphinxcontrib-napoleon==0.7; extra == "docs-strict"
Requires-Dist: sphinx-autoapi==1.8.4; extra == "docs-strict"
Requires-Dist: Pygments==2.9.0; extra == "docs-strict"
Requires-Dist: myst_parser==0.18.0; extra == "docs-strict"
Requires-Dist: sphinx-reredirects==0.0.1; extra == "docs-strict"
Provides-Extra: linting-strict
Requires-Dist: flake8==5.0.0; extra == "linting-strict"
Dynamic: author
Dynamic: author-email
Dynamic: classifier
Dynamic: description
Dynamic: description-content-type
Dynamic: home-page
Dynamic: license
Dynamic: license-file
Dynamic: provides-extra
Dynamic: requires-dist
Dynamic: requires-python
Dynamic: summary
